setup.py
scripts/bot
telegram_bot/__init__.py
telegram_bot/base.py
telegram_bot/bot.py
telegram_bot/config.py
telegram_bot/crypt.py
telegram_bot/exceptions.py
telegram_bot/plugins/__init__.py
telegram_bot/plugins/ban.py
telegram_bot/plugins/base.py
telegram_bot/plugins/moderators.py
telegram_bot/types/__init__.py
telegram_bot/types/keyboard.py
telegram_bot/types/message.py
telegram_bot/utils/__init__.py
telegram_bot/utils/classes.py
telegram_bot/utils/dicts.py
telegram_bot/utils/functions.py
telegram_bot/utils/geo.py
telegram_bot/utils/paste.py
telegram_bot/utils/registering.py
telegram_bot/utils/telegram.py
tg_bot.egg-info/PKG-INFO
tg_bot.egg-info/SOURCES.txt
tg_bot.egg-info/dependency_links.txt
tg_bot.egg-info/not-zip-safe
tg_bot.egg-info/pbr.json
tg_bot.egg-info/top_level.txt