Metadata-Version: 1.1
Name: tg-bot
Version: 0.1.0
Summary: Framework for bot creation in Telegram.
